betterls/__init__.py
betterls/filenames.json
betterls/ls.py
betterls-1.3.1.dist-info/entry_points.txt
betterls-1.3.1.dist-info/LICENSE
betterls-1.3.1.dist-info/WHEEL
betterls-1.3.1.dist-info/METADATA
betterls-1.3.1.dist-info/RECORD
