Metadata-Version: 2.1
Name: betterls
Version: 1.3.1
Summary: Better ls command.
Home-page: https://github.com/RealCyGuy/betterls
License: MIT
Keywords: ls,cli,windows
Author: Cyrus Yip
Author-email: cyruscmyip1@gmail.com
Requires-Python: >=3.8,<4.0
Classifier: License :: OSI Approved :: MIT License
Classifier: Programming Language :: Python :: 3
Classifier: Programming Language :: Python :: 3.8
Requires-Dist: click (>=7.1.2,<8.0.0)
Requires-Dist: colorama (>=0.4.3,<0.5.0)
Project-URL: Issues, https://github.com/realcyguy/betterls/issues
Project-URL: Repository, https://github.com/RealCyGuy/betterls
